logthis/__init__.py
logthis/logger.py
logthisx-0.1.0.dist-info/licenses/LICENSE
logthisx-0.1.0.dist-info/METADATA
logthisx-0.1.0.dist-info/WHEEL
logthisx-0.1.0.dist-info/top_level.txt
logthisx-0.1.0.dist-info/RECORD
