Metadata-Version: 2.4
Name: logthisx
Version: 0.1.0
Summary: A lightweight Python logging utility with colors and timestamps.
Author-email: Kevin Gregoire <kevin.gregoire1004@gmail.com>
License: MIT
Project-URL: Homepage, https://github.com/laxyny/logthis
Classifier: Programming Language :: Python :: 3
Classifier: Operating System :: OS Independent
Requires-Python: >=3.7
License-File: LICENSE
Dynamic: license-file
